<annotation>
	<folder>images</folder>
	<filename>Screenshot from R0010028_st.MP4 - 1.jpg</filename>
	<path>/home/lauren/TensorFlow/penguin_detection_model/images/Screenshot from R0010028_st.MP4 - 1.jpg</path>
	<source>
		<database>Unknown</database>
	</source>
	<size>
		<width>3840</width>
		<height>1920</height>
		<depth>3</depth>
	</size>
	<segmented>0</segmented>
	<object>
		<name>researcher</name>
		<pose>Unspecified</pose>
		<truncated>0</truncated>
		<difficult>0</difficult>
		<bndbox>
			<xmin>2</xmin>
			<ymin>696</ymin>
			<xmax>826</xmax>
			<ymax>1788</ymax>
		</bndbox>
	</object>
	<object>
		<name>adult_standing_penguin</name>
		<pose>Unspecified</pose>
		<truncated>0</truncated>
		<difficult>0</difficult>
		<bndbox>
			<xmin>1336</xmin>
			<ymin>887</ymin>
			<xmax>1400</xmax>
			<ymax>1016</ymax>
		</bndbox>
	</object>
	<object>
		<name>adult_standing_penguin</name>
		<pose>Unspecified</pose>
		<truncated>0</truncated>
		<difficult>0</difficult>
		<bndbox>
			<xmin>1405</xmin>
			<ymin>886</ymin>
			<xmax>1492</xmax>
			<ymax>1060</ymax>
		</bndbox>
	</object>
	<object>
		<name>adult_standing_penguin</name>
		<pose>Unspecified</pose>
		<truncated>0</truncated>
		<difficult>0</difficult>
		<bndbox>
			<xmin>1497</xmin>
			<ymin>865</ymin>
			<xmax>1566</xmax>
			<ymax>1040</ymax>
		</bndbox>
	</object>
	<object>
		<name>adult_standing_penguin</name>
		<pose>Unspecified</pose>
		<truncated>0</truncated>
		<difficult>0</difficult>
		<bndbox>
			<xmin>1570</xmin>
			<ymin>874</ymin>
			<xmax>1674</xmax>
			<ymax>1108</ymax>
		</bndbox>
	</object>
	<object>
		<name>adult_standing_penguin</name>
		<pose>Unspecified</pose>
		<truncated>0</truncated>
		<difficult>0</difficult>
		<bndbox>
			<xmin>1562</xmin>
			<ymin>872</ymin>
			<xmax>1608</xmax>
			<ymax>1020</ymax>
		</bndbox>
	</object>
	<object>
		<name>adult_standing_penguin</name>
		<pose>Unspecified</pose>
		<truncated>0</truncated>
		<difficult>0</difficult>
		<bndbox>
			<xmin>1666</xmin>
			<ymin>875</ymin>
			<xmax>1775</xmax>
			<ymax>1109</ymax>
		</bndbox>
	</object>
	<object>
		<name>adult_standing_penguin</name>
		<pose>Unspecified</pose>
		<truncated>0</truncated>
		<difficult>0</difficult>
		<bndbox>
			<xmin>1661</xmin>
			<ymin>868</ymin>
			<xmax>1714</xmax>
			<ymax>1016</ymax>
		</bndbox>
	</object>
	<object>
		<name>adult_standing_penguin</name>
		<pose>Unspecified</pose>
		<truncated>0</truncated>
		<difficult>0</difficult>
		<bndbox>
			<xmin>1869</xmin>
			<ymin>866</ymin>
			<xmax>2050</xmax>
			<ymax>1205</ymax>
		</bndbox>
	</object>
	<object>
		<name>adult_standing_penguin</name>
		<pose>Unspecified</pose>
		<truncated>0</truncated>
		<difficult>0</difficult>
		<bndbox>
			<xmin>2002</xmin>
			<ymin>876</ymin>
			<xmax>2097</xmax>
			<ymax>1094</ymax>
		</bndbox>
	</object>
	<object>
		<name>adult_standing_penguin</name>
		<pose>Unspecified</pose>
		<truncated>0</truncated>
		<difficult>0</difficult>
		<bndbox>
			<xmin>2071</xmin>
			<ymin>874</ymin>
			<xmax>2163</xmax>
			<ymax>1130</ymax>
		</bndbox>
	</object>
	<object>
		<name>adult_standing_penguin</name>
		<pose>Unspecified</pose>
		<truncated>0</truncated>
		<difficult>0</difficult>
		<bndbox>
			<xmin>2154</xmin>
			<ymin>910</ymin>
			<xmax>2252</xmax>
			<ymax>1092</ymax>
		</bndbox>
	</object>
	<object>
		<name>researcher</name>
		<pose>Unspecified</pose>
		<truncated>0</truncated>
		<difficult>0</difficult>
		<bndbox>
			<xmin>3331</xmin>
			<ymin>974</ymin>
			<xmax>3366</xmax>
			<ymax>1036</ymax>
		</bndbox>
	</object>
</annotation>
